LICENSE.md
MANIFEST.in
README.md
setup.py
admin_star/__init__.py
admin_star/admin.py
admin_star/apps.py
admin_star/forms.py
admin_star/models.py
admin_star/tests.py
admin_star/urls.py
admin_star/utils.py
admin_star/views.py
admin_star/migrations/__init__.py
admin_star/static/css/forms.css
admin_star/static/css/widgets.css
admin_star/static/css/maps/horizontal-layout-dark/style.css.map
admin_star/static/css/maps/horizontal-layout-light/style.css.map
admin_star/static/css/maps/vertical-layout-dark/style.css.map
admin_star/static/css/maps/vertical-layout-light/style.css.map
admin_star/static/css/vertical-layout-light/style.css
admin_star/static/fonts/Manrope/Manrope-Bold.eot
admin_star/static/fonts/Manrope/Manrope-Bold.ttf
admin_star/static/fonts/Manrope/Manrope-Bold.woff
admin_star/static/fonts/Manrope/Manrope-Bold.woff2
admin_star/static/fonts/Manrope/Manrope-ExtraBold.eot
admin_star/static/fonts/Manrope/Manrope-ExtraBold.ttf
admin_star/static/fonts/Manrope/Manrope-ExtraBold.woff
admin_star/static/fonts/Manrope/Manrope-ExtraBold.woff2
admin_star/static/fonts/Manrope/Manrope-ExtraLight.eot
admin_star/static/fonts/Manrope/Manrope-ExtraLight.ttf
admin_star/static/fonts/Manrope/Manrope-ExtraLight.woff
admin_star/static/fonts/Manrope/Manrope-ExtraLight.woff2
admin_star/static/fonts/Manrope/Manrope-Light.eot
admin_star/static/fonts/Manrope/Manrope-Light.ttf
admin_star/static/fonts/Manrope/Manrope-Light.woff
admin_star/static/fonts/Manrope/Manrope-Light.woff2
admin_star/static/fonts/Manrope/Manrope-Medium.eot
admin_star/static/fonts/Manrope/Manrope-Medium.ttf
admin_star/static/fonts/Manrope/Manrope-Medium.woff
admin_star/static/fonts/Manrope/Manrope-Medium.woff2
admin_star/static/fonts/Manrope/Manrope-Regular.eot
admin_star/static/fonts/Manrope/Manrope-Regular.ttf
admin_star/static/fonts/Manrope/Manrope-Regular.woff
admin_star/static/fonts/Manrope/Manrope-Regular.woff2
admin_star/static/fonts/Manrope/Manrope-SemiBold.eot
admin_star/static/fonts/Manrope/Manrope-SemiBold.ttf
django_admin_star.egg-info/PKG-INFO
django_admin_star.egg-info/SOURCES.txt
django_admin_star.egg-info/dependency_links.txt
django_admin_star.egg-info/not-zip-safe
django_admin_star.egg-info/top_level.txt
